dp_serial/__init__.py
dp_serial/client/__init__.py
dp_serial/client/client.py
dp_serial/client/diffprivlib.py
dp_serial/opendp_logger/__init__.py
dp_serial/opendp_logger/comb.py
dp_serial/opendp_logger/meas.py
dp_serial/opendp_logger/mods.py
dp_serial/opendp_logger/trans.py
dp_serial-0.1.5.dist-info/LICENSE.md
dp_serial-0.1.5.dist-info/METADATA
dp_serial-0.1.5.dist-info/WHEEL
dp_serial-0.1.5.dist-info/top_level.txt
dp_serial-0.1.5.dist-info/RECORD
